LICENSE
README.md
setup.py
zoomds/__init__.py
zoomds/analysis.py
zoomds/cleaning.py
zoomds/cols_info.py
zoomds/data_preprocessing.py
zoomds/data_statistics.py
zoomds/logging_errors.py
zoomds/metrics.py
zoomds/model_specific.py
zoomds/validation.py
zoomds.egg-info/PKG-INFO
zoomds.egg-info/SOURCES.txt
zoomds.egg-info/dependency_links.txt
zoomds.egg-info/requires.txt
zoomds.egg-info/top_level.txt